salt_lsp/__init__.py
salt_lsp/__main__.py
salt_lsp/ast.py
salt_lsp/base_types.py
salt_lsp/cmds.py
salt_lsp/data/states.pickle
salt_lsp/document_symbols.py
salt_lsp/parser.py
salt_lsp/server.py
salt_lsp/utils.py
salt_lsp/workspace.py
salt_lsp-0.0.1.dist-info/entry_points.txt
salt_lsp-0.0.1.dist-info/LICENSE
salt_lsp-0.0.1.dist-info/WHEEL
salt_lsp-0.0.1.dist-info/METADATA
salt_lsp-0.0.1.dist-info/RECORD
