Metadata-Version: 2.1
Name: salt-lsp
Version: 0.0.1
Summary: Salt Language Server Protocol Server
License: Apache-2.0
Author: Dan Čermák
Author-email: dcermak@suse.com
Requires-Python: >=3.8,<4.0
Classifier: License :: OSI Approved :: Apache Software License
Classifier: Programming Language :: Python :: 3
Classifier: Programming Language :: Python :: 3.8
Classifier: Programming Language :: Python :: 3.9
Requires-Dist: PyYAML (>=5.4,<6.0)
Requires-Dist: pygls (>=0.10.2,<0.11.0)
